{
  "version": "7.0",
  "project": {
    "id": "project_1782139270293_cg7f8",
    "name": "Geox",
    "description": "",
    "updatedAt": "2026-06-22T14:43:18.041Z"
  },
  "systemConfig": {
    "projectName": "Geox",
    "lerpFactor": 15
  },
  "buildings": [
    {
      "id": "b_1782139385368",
      "name": "預設場域",
      "floors": [
        {
          "id": "f_1782139385368",
          "name": "1F",
          "imageUrl": null,
          "markers": [],
          "waypoints": [],
          "edges": [],
          "bounds": {
            "blX": 0,
            "blY": 0,
            "trX": 100,
            "trY": 100
          }
        }
      ]
    }
  ]
}
